flytrap/__init__.py
flytrap/__main__.py
flytrap/app.py
flytrap/cli.py
flytrap/configs.py
flytrap/sessions.py
flytrap/short_url.py
flytrap/utils.py
flytrap/static/js/detectors.js
flytrap/static/js/services_detector.js
flytrap/static/js/utils.js
flytrap/templates/redirect.html
flytrap/templates/redirect_demo.html
flytrap-0.2.4.dist-info/LICENSE
flytrap-0.2.4.dist-info/METADATA
flytrap-0.2.4.dist-info/WHEEL
flytrap-0.2.4.dist-info/entry_points.txt
flytrap-0.2.4.dist-info/top_level.txt
flytrap-0.2.4.dist-info/RECORD
