Metadata-Version: 2.1
Name: flytrap
Version: 0.2.4
Summary: People tracker on the Internet. Catch a user using your URL!
Home-page: https://github.com/dodo325/flytrap/
Author: dodo325
Author-email: dodo101000101@gmail.com
License: Apache Software License 2.0
Keywords: flytrap
Classifier: Environment :: Console
Classifier: Intended Audience :: Developers
Classifier: License :: OSI Approved :: MIT License
Classifier: Natural Language :: English
Classifier: Programming Language :: Python
Classifier: Programming Language :: Python :: 3
Classifier: Programming Language :: Python :: 3.8
Classifier: Programming Language :: Python :: 3.9
Classifier: Programming Language :: Python :: 3.10
Classifier: Programming Language :: Python :: Implementation :: PyPy
Classifier: Topic :: Software Development
Requires-Python: >=3.8
License-File: LICENSE
Requires-Dist: rich
Requires-Dist: typer[all]
Requires-Dist: Flask
Requires-Dist: Flask-Session
Requires-Dist: flask-cors
Requires-Dist: Jinja2
Requires-Dist: MarkupSafe
Requires-Dist: itsdangerous
Requires-Dist: pyngrok
Provides-Extra: tests
Requires-Dist: rich ; extra == 'tests'
Requires-Dist: typer[all] ; extra == 'tests'
Requires-Dist: Flask ; extra == 'tests'
Requires-Dist: Flask-Session ; extra == 'tests'
Requires-Dist: flask-cors ; extra == 'tests'
Requires-Dist: Jinja2 ; extra == 'tests'
Requires-Dist: MarkupSafe ; extra == 'tests'
Requires-Dist: itsdangerous ; extra == 'tests'
Requires-Dist: pyngrok ; extra == 'tests'
Requires-Dist: uvicorn[standard] ; extra == 'tests'
Requires-Dist: pre-commit ; extra == 'tests'
Requires-Dist: bump2version (==1.0.1) ; extra == 'tests'
Requires-Dist: wheel (==0.37.1) ; extra == 'tests'
Requires-Dist: watchdog (==2.1.7) ; extra == 'tests'
Requires-Dist: flake8 (==4.0.1) ; extra == 'tests'
Requires-Dist: tox (==3.25.0) ; extra == 'tests'
Requires-Dist: coverage (==6.3.2) ; extra == 'tests'
Requires-Dist: Sphinx (==4.5.0) ; extra == 'tests'
Requires-Dist: furo (==2022.4.7) ; extra == 'tests'
Requires-Dist: twine (==4.0.0) ; extra == 'tests'
Requires-Dist: pep517 (==0.12.0) ; extra == 'tests'
Requires-Dist: click (==7.1.2) ; extra == 'tests'
Requires-Dist: pytest (==7.1.1) ; extra == 'tests'
Requires-Dist: pytest-runner (==5.1) ; extra == 'tests'
Requires-Dist: black (==21.7b0) ; extra == 'tests'
